tests/__init__.py
tests/test_exceptions.py
tests/test_weather_client.py
weather_api_wrapper/__init__.py
weather_api_wrapper/cli.py
weather_api_wrapper/exceptions.py
weather_api_wrapper/version.py
weather_api_wrapper/weather_client.py
weather_api_wrapper-0.1.6.dist-info/LICENSE
weather_api_wrapper-0.1.6.dist-info/METADATA
weather_api_wrapper-0.1.6.dist-info/WHEEL
weather_api_wrapper-0.1.6.dist-info/entry_points.txt
weather_api_wrapper-0.1.6.dist-info/top_level.txt
weather_api_wrapper-0.1.6.dist-info/RECORD
