Metadata-Version: 2.1
Name: weather_api_wrapper
Version: 0.1.6
Summary: A Python wrapper for the OpenWeatherMap API
Home-page: https://github.com/pyaustine/weather-api-wrapper.git
Author: Austin Ayah
Author-email: ayahaustine@gmail.com
Classifier: Programming Language :: Python :: 3
Classifier: License :: OSI Approved :: MIT License
Classifier: Operating System :: OS Independent
Requires-Python: >=3.6
License-File: LICENSE
Requires-Dist: requests
